{
  "maintenanceData": [
    { "year": "2026", "cost": 450 },
    { "year": "2027", "cost": 600 },
    { "year": "2028", "cost": 1200 },
    { "year": "2029", "cost": 850 },
    { "year": "2030", "cost": 2100 }
  ],
  "findings": [
    { "label": "Right fender scratch", "severity": "warning", "cost": "$150-$300" },
    { "label": "Battery health at 87%", "severity": "info", "cost": "Monitor" },
    { "label": "Tires at 60% tread", "severity": "info", "cost": "$400-$600" }
  ],
  "overviewStats": [
    { "label": "Condition", "value": "8.2/10", "color": "var(--color-emerald)" },
    { "label": "Market Value", "value": "$15.5k", "color": "var(--color-primary)" },
    { "label": "Issues", "value": "1", "color": "var(--color-warning)" }
  ],
  "vehicleSpecs": [
    { "label": "VIN", "value": "JTDKNAM32X012****", "mono": true },
    { "label": "Make / Model", "value": "Toyota Prius", "bold": true },
    { "label": "Year", "value": "2019" },
    { "label": "Odometer", "value": "~45,210 mi" },
    { "label": "Previous Owners", "value": "2" },
    { "label": "Last Service", "value": "2026-01-15" }
  ],
  "mechanics": [
    { "name": "Joe's Auto Repair", "dist": "2.1 mi", "rating": "4.8★" },
    { "name": "Elite Diagnostics", "dist": "3.5 mi", "rating": "4.9★" }
  ]
}
